swissarmykit/__init__.py
swissarmykit/admin.py
swissarmykit/app.py
swissarmykit/conf.py
swissarmykit/crawler/__init__.py
swissarmykit/crawler/mini/Crawler.py
swissarmykit/crawler/mini/__init__.py
swissarmykit/data/Address.py
swissarmykit/data/AddressData.py
swissarmykit/data/BSoup.py
swissarmykit/data/Dict.py
swissarmykit/data/DictData.py
swissarmykit/data/DupData.py
swissarmykit/data/JsonData.py
swissarmykit/data/__init__.py
swissarmykit/dataset/__init__.py
swissarmykit/dataset/canada/CanadaUtils.py
swissarmykit/dataset/canada/__init__.py
swissarmykit/dataset/usa/USUtils.py
swissarmykit/dataset/usa/__init__.py
swissarmykit/db/__init__.py
swissarmykit/db/database.py
swissarmykit/db/mongodb.py
swissarmykit/db/other_mongodb.py
swissarmykit/db/record.py
swissarmykit/db/redisconnect.py
swissarmykit/db/schema.py
swissarmykit/db/mysql/__init__.py
swissarmykit/db/mysql/database.py
swissarmykit/db/mysql/record.py
swissarmykit/db/mysql/schema.py
swissarmykit/image/__init__.py
swissarmykit/image/imageutils.py
swissarmykit/lib/__init__.py
swissarmykit/lib/baseobject.py
swissarmykit/lib/cache.py
swissarmykit/lib/core.py
swissarmykit/lib/inspector.py
swissarmykit/office/__init__.py
swissarmykit/office/excelutils.py
swissarmykit/office/pdfutils.py
swissarmykit/req/BotDetect.py
swissarmykit/req/FileThread.py
swissarmykit/req/Headers.py
swissarmykit/req/PathUtils.py
swissarmykit/req/RequestBase.py
swissarmykit/req/RequestCommon.py
swissarmykit/req/UserAgent.py
swissarmykit/req/__init__.py
swissarmykit/service/__init__.py
swissarmykit/service/googlesheet.py
swissarmykit/service/slackutils.py
swissarmykit/templates/__init__.py
swissarmykit/templates/config_default.py
swissarmykit/templates/definitions.py
swissarmykit/templates/definitions_tmp.py
swissarmykit/test/__init__.py
swissarmykit/test/test_conf.py
swissarmykit/test/test_template.py
swissarmykit/test/db/__init__.py
swissarmykit/test/db/test_mongodb.py
swissarmykit/test/utils/__init__.py
swissarmykit-1.1.7.dist-info/LICENSE
swissarmykit-1.1.7.dist-info/METADATA
swissarmykit-1.1.7.dist-info/WHEEL
swissarmykit-1.1.7.dist-info/top_level.txt
swissarmykit-1.1.7.dist-info/RECORD
