Metadata-Version: 2.1
Name: swissarmykit
Version: 1.1.7
Summary: Swiss Army Kit
Home-page: https://github.com/pypa/swissarmykit
Author: Will Nguyen
Author-email: will.ng.nguyen@gmail.com
License: UNKNOWN
Platform: UNKNOWN
Classifier: Programming Language :: Python :: 3
Classifier: License :: OSI Approved :: MIT License
Classifier: Operating System :: OS Independent
Requires-Dist: aiohttp
Requires-Dist: slack-sdk
Requires-Dist: fake-useragent
Requires-Dist: beautifulsoup4
Requires-Dist: mongoengine
Requires-Dist: redis
Requires-Dist: peewee
Requires-Dist: requests
Requires-Dist: openpyxl
Requires-Dist: validate-email
Requires-Dist: validators
Requires-Dist: PyExecJS
Requires-Dist: Pillow
Requires-Dist: pandas
Requires-Dist: scikit-image
Requires-Dist: texttable
Requires-Dist: wordcloud
Requires-Dist: nltk
Requires-Dist: usaddress
Requires-Dist: us
Requires-Dist: pyap
Requires-Dist: brotli
Requires-Dist: cfscrape
Requires-Dist: Faker
Requires-Dist: google-auth-oauthlib
Requires-Dist: google-auth
